Metadata-Version: 2.4
Name: deepcubeai
Version: 0.2.1
Summary: Learning Discrete World Models for Heuristic Search
Project-URL: GitHub, https://github.com/misaghsoltani/DeepCubeAI/
Project-URL: Paper, https://rlj.cs.umass.edu/2024/papers/Paper225.html
Author-email: Misagh Soltani <msoltani@email.sc.edu>
License-Expression: MIT
License-File: LICENSE
Keywords: DeepCube,DeepCubeA,DeepCubeAI,DeepXube,Q*,Q* search,Rubik's Cube,Sokoban,deep learning,deep q-learning,deep q-network,deep reinforcement learning,discrete world model,heuristic search,model-based reinforcement learning,pathfinding,planning,reinforcement learning,search
Classifier: License :: OSI Approved :: MIT License
Classifier: Operating System :: OS Independent
Classifier: Programming Language :: Python :: 3
Classifier: Typing :: Typed
Requires-Python: <3.13,>=3.10
Requires-Dist: gymnasium<2,>=1.2.0
Requires-Dist: matplotlib<4,>=3.10.3
Requires-Dist: networkx<4,>=3.5
Requires-Dist: numpy<3,>=2.3.2
Requires-Dist: opencv-python<5,>=4.11.0.86
Requires-Dist: tensorboard<3,>=2.20.0
Requires-Dist: torch<3,>=2.2.2
